douyin_mcp_server_ali/__init__.py
douyin_mcp_server_ali/server.py
douyin_mcp_server_ali-1.2.0.dist-info/METADATA
douyin_mcp_server_ali-1.2.0.dist-info/WHEEL
douyin_mcp_server_ali-1.2.0.dist-info/entry_points.txt
douyin_mcp_server_ali-1.2.0.dist-info/licenses/LICENSE
douyin_mcp_server_ali-1.2.0.dist-info/RECORD
